{
  "db_name": "PostgreSQL",
  "query": "INSERT INTO onboarding_applications\n             (id, tenant_id, client_id, agent_id, branch_id, product_code,\n              current_status, otp_verified_at, consent_at, consent_terms_version,\n              submitted_at, created_at, updated_at)\n           VALUES ($1, $2, $3, $4, $5, $6, $7, $8, $9, $10, $11, $12, $13)\n           ON CONFLICT (id) DO NOTHING",
  "describe": {
    "columns": [],
    "parameters": {
      "Left": [
        "Uuid",
        "Uuid",
        "Uuid",
        "Uuid",
        "Uuid",
        "Text",
        "Text",
        "Timestamptz",
        "Timestamptz",
        "Text",
        "Timestamptz",
        "Timestamptz",
        "Timestamptz"
      ]
    },
    "nullable": []
  },
  "hash": "320c7d97bd56fa3b3f849917e73f3b5a959a107d243bbad47b24590f7aacc30a"
}
